torch_sparse/__init__.py
torch_sparse/add.py
torch_sparse/bandwidth.py
torch_sparse/cat.py
torch_sparse/coalesce.py
torch_sparse/convert.py
torch_sparse/diag.py
torch_sparse/eye.py
torch_sparse/index_select.py
torch_sparse/masked_select.py
torch_sparse/matmul.py
torch_sparse/metis.py
torch_sparse/mul.py
torch_sparse/narrow.py
torch_sparse/permute.py
torch_sparse/reduce.py
torch_sparse/rw.py
torch_sparse/saint.py
torch_sparse/sample.py
torch_sparse/select.py
torch_sparse/spadd.py
torch_sparse/spmm.py
torch_sparse/spspmm.py
torch_sparse/storage.py
torch_sparse/tensor.py
torch_sparse/testing.py
torch_sparse/transpose.py
torch_sparse/typing.py
torch_sparse/utils.py
torch_sparse_carate-0.6.17.dist-info/LICENSE
torch_sparse_carate-0.6.17.dist-info/METADATA
torch_sparse_carate-0.6.17.dist-info/WHEEL
torch_sparse_carate-0.6.17.dist-info/top_level.txt
torch_sparse_carate-0.6.17.dist-info/RECORD
