Metadata-Version: 2.1
Name: torch-sparse-carate
Version: 0.6.17
Summary: PyTorch Extension Library of Optimized Autograd Sparse Matrix Operations
Home-page: https://codeberg.org/sail.black/pytorch_sparse_carate.git
Download-URL: https://codeberg.org/sail.black/pytorch_sparse_carate.git/archive/0.6.17.tar.gz
Author: Julian M. Kleber
Author-email: julian.kleber@sail.black
Keywords: pytorch,sparse,sparse-matrices,autograd
Classifier: Development Status :: 5 - Production/Stable
Classifier: License :: OSI Approved :: MIT License
Classifier: Programming Language :: Python
Classifier: Programming Language :: Python :: 3.7
Classifier: Programming Language :: Python :: 3.8
Classifier: Programming Language :: Python :: 3.9
Classifier: Programming Language :: Python :: 3.10
Classifier: Programming Language :: Python :: 3 :: Only
Requires-Python: >=3.7
License-File: LICENSE
Requires-Dist: scipy
Requires-Dist: torch
Provides-Extra: test
Requires-Dist: pytest ; extra == 'test'
Requires-Dist: pytest-cov ; extra == 'test'
